[
  {"genre":"Alternative Music"},
  {"genre":"Blues"},
  {"genre":"Classical Music"},
  {"genre":"Country Music"},
  {"genre":"Dance Music"},
  {"genre":"Easy Listening"},
  {"genre":"Electronic Music"},
  {"genre":"European Music (Folk / Pop)"},
  {"genre":"Hip Hop / Rap"},
  {"genre":"Indie Pop"},
  {"genre":"Inspirational (incl. Gospel)"},
  {"genre":"Asian Pop (J-Pop, K-pop)"},
  {"genre":"Jazz"},
  {"genre":"Latin Music"},
  {"genre":"New Age"},
  {"genre":"Opera"},
  {"genre":"Pop (Popular music)"},
  {"genre":"R&B / Soul"},
  {"genre":"Reggae"},
  {"genre":"Rock"},
  {"genre":"Singer / Songwriter (inc. Folk)"},
  {"genre":"World Music / Beats"}
]
